<?xml version="1.0" encoding="utf-8"?>
<ItemAssembly name="ITAPuzzle1a" description="" hideinmenus="false">
  <Item name="" identifier="alienitemcontainerlarge" ID="9" rect="-383,-307,123,62"  rotation="0" scale="0.5" spritecolor="255,255,255,255" inventoryiconcolor="255,255,255,255" containercolor="255,255,255,255" condition="100" tags="aliencontainer,container0" displaysidebysidewhenlinked="False" disallowedupgrades="" spritedepth="0.84" hiddeningame="False">
    <ItemContainer containablerestrictions="" autofill="True" pickingtime="0" canbepicked="False" allowingameediting="False" msg="" contained="0,0,0,0,0" />
  </Item>
  <Structure name="Ruin Wall Small Horizontal" identifier="RuinWallHorizontalSmall" ID="20" rect="-416,-114,320,48" specialtag="" spritecolor="255,255,255,255" usedropshadow="False" dropshadowoffset="0,0" scale="1" texturescale="1,1" textureoffset="0,0" noaitarget="True" disallowedupgrades="" spritedepth="0.062" hiddeningame="False" />
  <Structure name="Ruin Wall Small Horizontal" identifier="RuinWallHorizontalSmall" ID="19" rect="98,-114,112,48" specialtag="" spritecolor="255,255,255,255" usedropshadow="False" dropshadowoffset="0,0" scale="1" texturescale="1,1" textureoffset="0,0" noaitarget="True" disallowedupgrades="" spritedepth="0.062" hiddeningame="False" />
  <Structure name="Ruin Wall Small Vertical" identifier="RuinWallVerticalSmall" ID="16" rect="-464,432,48,320" specialtag="" spritecolor="255,255,255,255" usedropshadow="False" dropshadowoffset="0,0" scale="1" texturescale="1,1" textureoffset="0,0" noaitarget="True" disallowedupgrades="" spritedepth="0.063" hiddeningame="False" />
  <Structure name="Ruin Wall Small Horizontal" identifier="RuinWallHorizontalSmall" ID="15" rect="-416,432,832,48" specialtag="" spritecolor="255,255,255,255" usedropshadow="False" dropshadowoffset="0,0" scale="1" texturescale="1,1" textureoffset="0,0" noaitarget="True" disallowedupgrades="" spritedepth="0.062" hiddeningame="False" />
  <Structure name="Ruin Wall Small Horizontal" identifier="RuinWallHorizontalSmall" ID="14" rect="-208,176,416,48" specialtag="" spritecolor="255,255,255,255" usedropshadow="False" dropshadowoffset="0,0" scale="1" texturescale="1,1" textureoffset="0,0" noaitarget="True" disallowedupgrades="" spritedepth="0.062" hiddeningame="False" />
  <Structure name="Ruin Wall Small Vertical" identifier="RuinWallVerticalSmall" ID="13" rect="160,128,48,240" flippedx="true" specialtag="" spritecolor="255,255,255,255" usedropshadow="False" dropshadowoffset="0,0" scale="1" texturescale="1,1" textureoffset="0,0" noaitarget="True" disallowedupgrades="" spritedepth="0.063" hiddeningame="False" />
  <Structure name="Ruin Wall Small Vertical" identifier="RuinWallVerticalSmall" ID="12" rect="-464,-96,48,322" specialtag="" spritecolor="255,255,255,255" usedropshadow="False" dropshadowoffset="0,0" scale="1" texturescale="1,1" textureoffset="0,0" noaitarget="True" disallowedupgrades="" spritedepth="0.063" hiddeningame="False" />
  <Structure name="Ruin Wall Small Vertical" identifier="RuinWallVerticalSmall" ID="11" rect="416,432,48,850" flippedx="true" specialtag="" spritecolor="255,255,255,255" usedropshadow="False" dropshadowoffset="0,0" scale="1" texturescale="1,1" textureoffset="0,0" noaitarget="True" disallowedupgrades="" spritedepth="0.063" hiddeningame="False" />
  <Structure name="Ruin Wall Small Horizontal" identifier="RuinWallHorizontalSmall" ID="10" rect="-416,-370,832,48" specialtag="" spritecolor="255,255,255,255" usedropshadow="False" dropshadowoffset="0,0" scale="1" texturescale="1,1" textureoffset="0,0" noaitarget="True" disallowedupgrades="" spritedepth="0.062" hiddeningame="False" />
  <Item name="" identifier="aliendoor" noninteractable="True" ID="22" rect="-16,384,48,208" linked=""  rotation="0" scale="1" spritecolor="255,255,255,255" inventoryiconcolor="255,255,255,255" containercolor="255,255,255,255" condition="100" tags="alien,aliendoor" displaysidebysidewhenlinked="False" disallowedupgrades="" spritedepth="0.8" hiddeningame="False">
    <Door openingspeed="3" closingspeed="3" togglecooldown="1" isopen="False" usebetweenoutpostmodules="True" pickingtime="30" canbepicked="False" allowingameediting="True" msg="ItemMsgForceOpenCrowbar">
      <requireditem items="nopick" type="Equipped" optional="false" ignoreineditor="false" />
    </Door>
    <ConnectionPanel locked="False" pickingtime="0" canbepicked="False" allowingameediting="True" msg="">
      <input name="toggle">
        <link w="58" />
      </input>
      <input name="set_state">
        <link w="59" />
        <link w="60" />
      </input>
      <output name="state_out">
        <link w="61" />
        <link w="62" />
        <link w="63" />
      </output>
    </ConnectionPanel>
  </Item>
  <Item name="" identifier="aliendoor" noninteractable="True" ID="21" rect="-140,-163,48,208" linked=""  rotation="0" scale="1" spritecolor="255,255,255,255" inventoryiconcolor="255,255,255,255" containercolor="255,255,255,255" condition="100" tags="alien,aliendoor" displaysidebysidewhenlinked="False" disallowedupgrades="" spritedepth="0.8" hiddeningame="False">
    <Door openingspeed="3" closingspeed="3" togglecooldown="1" isopen="False" usebetweenoutpostmodules="True" pickingtime="30" canbepicked="False" allowingameediting="True" msg="ItemMsgForceOpenCrowbar">
      <requireditem items="nopick" type="Equipped" optional="false" ignoreineditor="false" />
    </Door>
    <ConnectionPanel locked="False" pickingtime="0" canbepicked="False" allowingameediting="True" msg="">
      <input name="toggle" />
      <input name="set_state">
        <link w="56" />
      </input>
      <output name="state_out">
        <link w="57" />
      </output>
    </ConnectionPanel>
  </Item>
  <Item name="" identifier="orangewire" ID="169" rect="50075,-10232,42,16"  rotation="0" scale="0.5" spritecolor="255,140,13,255" inventoryiconcolor="255,140,13,255" containercolor="255,255,255,255" condition="100" tags="smallitem,wire" displaysidebysidewhenlinked="False" disallowedupgrades="" spritedepth="0.55" hiddeningame="True" hideinassemblypreview="true">
    <Holdable holdpos="0,0" holdangle="0" swingamount="0,0" swingspeed="0" swingwhenholding="False" swingwhenaiming="False" swingwhenusing="False" pickingtime="0" canbepicked="True" allowingameediting="True" msg="ItemMsgPickUpSelect" />
    <Wire pickingtime="0" canbepicked="False" allowingameediting="True" msg="" nodes="37;22;312;152" />
  </Item>
  <Item name="" identifier="orangewire" ID="168" rect="50075,-10232,42,16"  rotation="0" scale="0.5" spritecolor="255,140,13,255" inventoryiconcolor="255,140,13,255" containercolor="255,255,255,255" condition="100" tags="smallitem,wire" displaysidebysidewhenlinked="False" disallowedupgrades="" spritedepth="0.55" hiddeningame="True" hideinassemblypreview="true">
    <Holdable holdpos="0,0" holdangle="0" swingamount="0,0" swingspeed="0" swingwhenholding="False" swingwhenaiming="False" swingwhenusing="False" pickingtime="0" canbepicked="True" allowingameediting="True" msg="ItemMsgPickUpSelect" />
    <Wire pickingtime="0" canbepicked="False" allowingameediting="True" msg="" nodes="-35;22;-310;150" />
  </Item>
  <Item name="" identifier="orangewire" ID="167" rect="50075,-10232,42,16"  rotation="0" scale="0.5" spritecolor="255,140,13,255" inventoryiconcolor="255,140,13,255" containercolor="255,255,255,255" condition="100" tags="smallitem,wire" displaysidebysidewhenlinked="False" disallowedupgrades="" spritedepth="0.55" hiddeningame="True" hideinassemblypreview="true">
    <Holdable holdpos="0,0" holdangle="0" swingamount="0,0" swingspeed="0" swingwhenholding="False" swingwhenaiming="False" swingwhenusing="False" pickingtime="0" canbepicked="True" allowingameediting="True" msg="ItemMsgPickUpSelect" />
    <Wire pickingtime="0" canbepicked="False" allowingameediting="True" msg="" nodes="1;-41;1;-138" />
  </Item>
  <Item name="" identifier="orangewire" ID="166" rect="50075,-10232,42,16"  rotation="0" scale="0.5" spritecolor="255,140,13,255" inventoryiconcolor="255,140,13,255" containercolor="255,255,255,255" condition="100" tags="smallitem,wire" displaysidebysidewhenlinked="False" disallowedupgrades="" spritedepth="0.55" hiddeningame="True" hideinassemblypreview="true">
    <Holdable holdpos="0,0" holdangle="0" swingamount="0,0" swingspeed="0" swingwhenholding="False" swingwhenaiming="False" swingwhenusing="False" pickingtime="0" canbepicked="True" allowingameediting="True" msg="ItemMsgPickUpSelect" />
    <Wire pickingtime="0" canbepicked="False" allowingameediting="True" msg="" nodes="37;-20;314;-138" />
  </Item>
  <Item name="" identifier="blackwire" ID="165" rect="50075,-10232,42,16"  rotation="0" scale="0.5" spritecolor="50,50,50,255" inventoryiconcolor="50,50,50,255" containercolor="255,255,255,255" condition="100" tags="smallitem,wire" displaysidebysidewhenlinked="False" disallowedupgrades="" spritedepth="0.55" hiddeningame="True" hideinassemblypreview="true">
    <Holdable holdpos="0,0" holdangle="0" swingamount="0,0" swingspeed="0" swingwhenholding="False" swingwhenaiming="False" swingwhenusing="False" pickingtime="0" canbepicked="True" allowingameediting="True" msg="ItemMsgPickUpSelect" />
    <Wire pickingtime="0" canbepicked="False" allowingameediting="True" msg="" nodes="-72.5;57.5;1;-138" />
  </Item>
  <Item name="" identifier="blackwire" ID="164" rect="50075,-10232,42,16"  rotation="0" scale="0.5" spritecolor="50,50,50,255" inventoryiconcolor="50,50,50,255" containercolor="255,255,255,255" condition="100" tags="smallitem,wire" displaysidebysidewhenlinked="False" disallowedupgrades="" spritedepth="0.55" hiddeningame="True" hideinassemblypreview="true">
    <Holdable holdpos="0,0" holdangle="0" swingamount="0,0" swingspeed="0" swingwhenholding="False" swingwhenaiming="False" swingwhenusing="False" pickingtime="0" canbepicked="True" allowingameediting="True" msg="ItemMsgPickUpSelect" />
    <Wire pickingtime="0" canbepicked="False" allowingameediting="True" msg="" nodes="-72.5;57.5;314;-138" />
  </Item>
  <Item name="" identifier="blackwire" ID="163" rect="50075,-10232,42,16"  rotation="0" scale="0.5" spritecolor="50,50,50,255" inventoryiconcolor="50,50,50,255" containercolor="255,255,255,255" condition="100" tags="smallitem,wire" displaysidebysidewhenlinked="False" disallowedupgrades="" spritedepth="0.55" hiddeningame="True" hideinassemblypreview="true">
    <Holdable holdpos="0,0" holdangle="0" swingamount="0,0" swingspeed="0" swingwhenholding="False" swingwhenaiming="False" swingwhenusing="False" pickingtime="0" canbepicked="True" allowingameediting="True" msg="ItemMsgPickUpSelect" />
    <Wire pickingtime="0" canbepicked="False" allowingameediting="True" msg="" nodes="-40.5;57.5;314;-138" />
  </Item>
  <Item name="" identifier="blackwire" ID="162" rect="50075,-10232,42,16"  rotation="0" scale="0.5" spritecolor="50,50,50,255" inventoryiconcolor="50,50,50,255" containercolor="255,255,255,255" condition="100" tags="smallitem,wire" displaysidebysidewhenlinked="False" disallowedupgrades="" spritedepth="0.55" hiddeningame="True" hideinassemblypreview="true">
    <Holdable holdpos="0,0" holdangle="0" swingamount="0,0" swingspeed="0" swingwhenholding="False" swingwhenaiming="False" swingwhenusing="False" pickingtime="0" canbepicked="True" allowingameediting="True" msg="ItemMsgPickUpSelect" />
    <Wire pickingtime="0" canbepicked="False" allowingameediting="True" msg="" nodes="-40.5;57.5;312;152" />
  </Item>
  <Item name="" identifier="blackwire" ID="161" rect="50075,-10232,42,16"  rotation="0" scale="0.5" spritecolor="50,50,50,255" inventoryiconcolor="50,50,50,255" containercolor="255,255,255,255" condition="100" tags="smallitem,wire" displaysidebysidewhenlinked="False" disallowedupgrades="" spritedepth="0.55" hiddeningame="True" hideinassemblypreview="true">
    <Holdable holdpos="0,0" holdangle="0" swingamount="0,0" swingspeed="0" swingwhenholding="False" swingwhenaiming="False" swingwhenusing="False" pickingtime="0" canbepicked="True" allowingameediting="True" msg="ItemMsgPickUpSelect" />
    <Wire pickingtime="0" canbepicked="False" allowingameediting="True" msg="" nodes="-8.5;57.5;312;152" />
  </Item>
  <Item name="" identifier="blackwire" ID="160" rect="50075,-10232,42,16"  rotation="0" scale="0.5" spritecolor="50,50,50,255" inventoryiconcolor="50,50,50,255" containercolor="255,255,255,255" condition="100" tags="smallitem,wire" displaysidebysidewhenlinked="False" disallowedupgrades="" spritedepth="0.55" hiddeningame="True" hideinassemblypreview="true">
    <Holdable holdpos="0,0" holdangle="0" swingamount="0,0" swingspeed="0" swingwhenholding="False" swingwhenaiming="False" swingwhenusing="False" pickingtime="0" canbepicked="True" allowingameediting="True" msg="ItemMsgPickUpSelect" />
    <Wire pickingtime="0" canbepicked="False" allowingameediting="True" msg="" nodes="23.5;57.5;-310;150" />
  </Item>
  <Item name="" identifier="blackwire" ID="159" rect="50075,-10232,42,16"  rotation="0" scale="0.5" spritecolor="50,50,50,255" inventoryiconcolor="50,50,50,255" containercolor="255,255,255,255" condition="100" tags="smallitem,wire" displaysidebysidewhenlinked="False" disallowedupgrades="" spritedepth="0.55" hiddeningame="True" hideinassemblypreview="true">
    <Holdable holdpos="0,0" holdangle="0" swingamount="0,0" swingspeed="0" swingwhenholding="False" swingwhenaiming="False" swingwhenusing="False" pickingtime="0" canbepicked="True" allowingameediting="True" msg="ItemMsgPickUpSelect" />
    <Wire pickingtime="0" canbepicked="False" allowingameediting="True" msg="" nodes="-72.5;73;314;-138" />
  </Item>
  <Item name="" identifier="blackwire" ID="158" rect="50075,-10232,42,16"  rotation="0" scale="0.5" spritecolor="50,50,50,255" inventoryiconcolor="50,50,50,255" containercolor="255,255,255,255" condition="100" tags="smallitem,wire" displaysidebysidewhenlinked="False" disallowedupgrades="" spritedepth="0.55" hiddeningame="True" hideinassemblypreview="true">
    <Holdable holdpos="0,0" holdangle="0" swingamount="0,0" swingspeed="0" swingwhenholding="False" swingwhenaiming="False" swingwhenusing="False" pickingtime="0" canbepicked="True" allowingameediting="True" msg="ItemMsgPickUpSelect" />
    <Wire pickingtime="0" canbepicked="False" allowingameediting="True" msg="" nodes="-72.5;73;1;-138" />
  </Item>
  <Item name="" identifier="blackwire" ID="157" rect="50075,-10232,42,16"  rotation="0" scale="0.5" spritecolor="50,50,50,255" inventoryiconcolor="50,50,50,255" containercolor="255,255,255,255" condition="100" tags="smallitem,wire" displaysidebysidewhenlinked="False" disallowedupgrades="" spritedepth="0.55" hiddeningame="True" hideinassemblypreview="true">
    <Holdable holdpos="0,0" holdangle="0" swingamount="0,0" swingspeed="0" swingwhenholding="False" swingwhenaiming="False" swingwhenusing="False" pickingtime="0" canbepicked="True" allowingameediting="True" msg="ItemMsgPickUpSelect" />
    <Wire pickingtime="0" canbepicked="False" allowingameediting="True" msg="" nodes="-72.5;73;1;1" />
  </Item>
  <Item name="" identifier="blackwire" ID="156" rect="50075,-10232,42,16"  rotation="0" scale="0.5" spritecolor="50,50,50,255" inventoryiconcolor="50,50,50,255" containercolor="255,255,255,255" condition="100" tags="smallitem,wire" displaysidebysidewhenlinked="False" disallowedupgrades="" spritedepth="0.55" hiddeningame="True" hideinassemblypreview="true">
    <Holdable holdpos="0,0" holdangle="0" swingamount="0,0" swingspeed="0" swingwhenholding="False" swingwhenaiming="False" swingwhenusing="False" pickingtime="0" canbepicked="True" allowingameediting="True" msg="ItemMsgPickUpSelect" />
    <Wire pickingtime="0" canbepicked="False" allowingameediting="True" msg="" nodes="-40.5;73;312;152" />
  </Item>
  <Item name="" identifier="blackwire" ID="155" rect="50075,-10232,42,16"  rotation="0" scale="0.5" spritecolor="50,50,50,255" inventoryiconcolor="50,50,50,255" containercolor="255,255,255,255" condition="100" tags="smallitem,wire" displaysidebysidewhenlinked="False" disallowedupgrades="" spritedepth="0.55" hiddeningame="True" hideinassemblypreview="true">
    <Holdable holdpos="0,0" holdangle="0" swingamount="0,0" swingspeed="0" swingwhenholding="False" swingwhenaiming="False" swingwhenusing="False" pickingtime="0" canbepicked="True" allowingameediting="True" msg="ItemMsgPickUpSelect" />
    <Wire pickingtime="0" canbepicked="False" allowingameediting="True" msg="" nodes="-40.5;73;314;-138" />
  </Item>
  <Item name="" identifier="blackwire" ID="154" rect="50075,-10232,42,16"  rotation="0" scale="0.5" spritecolor="50,50,50,255" inventoryiconcolor="50,50,50,255" containercolor="255,255,255,255" condition="100" tags="smallitem,wire" displaysidebysidewhenlinked="False" disallowedupgrades="" spritedepth="0.55" hiddeningame="True" hideinassemblypreview="true">
    <Holdable holdpos="0,0" holdangle="0" swingamount="0,0" swingspeed="0" swingwhenholding="False" swingwhenaiming="False" swingwhenusing="False" pickingtime="0" canbepicked="True" allowingameediting="True" msg="ItemMsgPickUpSelect" />
    <Wire pickingtime="0" canbepicked="False" allowingameediting="True" msg="" nodes="-40.5;73;1;1" />
  </Item>
  <Item name="" identifier="blackwire" ID="79" rect="50075,-10232,42,16"  rotation="0" scale="0.5" spritecolor="50,50,50,255" inventoryiconcolor="50,50,50,255" containercolor="255,255,255,255" condition="100" tags="smallitem,wire" displaysidebysidewhenlinked="False" disallowedupgrades="" spritedepth="0.55" hiddeningame="True" hideinassemblypreview="true">
    <Holdable holdpos="0,0" holdangle="0" swingamount="0,0" swingspeed="0" swingwhenholding="False" swingwhenaiming="False" swingwhenusing="False" pickingtime="0" canbepicked="True" allowingameediting="True" msg="ItemMsgPickUpSelect" />
    <Wire pickingtime="0" canbepicked="False" allowingameediting="True" msg="" nodes="-8.5;73;312;152" />
  </Item>
  <Item name="" identifier="blackwire" ID="78" rect="50075,-10232,42,16"  rotation="0" scale="0.5" spritecolor="50,50,50,255" inventoryiconcolor="50,50,50,255" containercolor="255,255,255,255" condition="100" tags="smallitem,wire" displaysidebysidewhenlinked="False" disallowedupgrades="" spritedepth="0.55" hiddeningame="True" hideinassemblypreview="true">
    <Holdable holdpos="0,0" holdangle="0" swingamount="0,0" swingspeed="0" swingwhenholding="False" swingwhenaiming="False" swingwhenusing="False" pickingtime="0" canbepicked="True" allowingameediting="True" msg="ItemMsgPickUpSelect" />
    <Wire pickingtime="0" canbepicked="False" allowingameediting="True" msg="" nodes="-8.5;73;1;1" />
  </Item>
  <Item name="" identifier="blackwire" ID="77" rect="50075,-10232,42,16"  rotation="0" scale="0.5" spritecolor="50,50,50,255" inventoryiconcolor="50,50,50,255" containercolor="255,255,255,255" condition="100" tags="smallitem,wire" displaysidebysidewhenlinked="False" disallowedupgrades="" spritedepth="0.55" hiddeningame="True" hideinassemblypreview="true">
    <Holdable holdpos="0,0" holdangle="0" swingamount="0,0" swingspeed="0" swingwhenholding="False" swingwhenaiming="False" swingwhenusing="False" pickingtime="0" canbepicked="True" allowingameediting="True" msg="ItemMsgPickUpSelect" />
    <Wire pickingtime="0" canbepicked="False" allowingameediting="True" msg="" nodes="24.5;73;-310;150" />
  </Item>
  <Item name="" identifier="blackwire" ID="76" rect="50075,-10232,42,16"  rotation="0" scale="0.5" spritecolor="50,50,50,255" inventoryiconcolor="50,50,50,255" containercolor="255,255,255,255" condition="100" tags="smallitem,wire" displaysidebysidewhenlinked="False" disallowedupgrades="" spritedepth="0.55" hiddeningame="True" hideinassemblypreview="true">
    <Holdable holdpos="0,0" holdangle="0" swingamount="0,0" swingspeed="0" swingwhenholding="False" swingwhenaiming="False" swingwhenusing="False" pickingtime="0" canbepicked="True" allowingameediting="True" msg="ItemMsgPickUpSelect" />
    <Wire pickingtime="0" canbepicked="False" allowingameediting="True" msg="" nodes="24.5;73;1;1" />
  </Item>
  <Item name="" identifier="blackwire" ID="75" rect="50075,-10232,42,16"  rotation="0" scale="0.5" spritecolor="50,50,50,255" inventoryiconcolor="50,50,50,255" containercolor="255,255,255,255" condition="100" tags="smallitem,wire" displaysidebysidewhenlinked="False" disallowedupgrades="" spritedepth="0.55" hiddeningame="True" hideinassemblypreview="true">
    <Holdable holdpos="0,0" holdangle="0" swingamount="0,0" swingspeed="0" swingwhenholding="False" swingwhenaiming="False" swingwhenusing="False" pickingtime="0" canbepicked="True" allowingameediting="True" msg="ItemMsgPickUpSelect" />
    <Wire pickingtime="0" canbepicked="False" allowingameediting="True" msg="" nodes="56.5;73;1;-138" />
  </Item>
  <Item name="" identifier="blackwire" ID="74" rect="50075,-10232,42,16"  rotation="0" scale="0.5" spritecolor="50,50,50,255" inventoryiconcolor="50,50,50,255" containercolor="255,255,255,255" condition="100" tags="smallitem,wire" displaysidebysidewhenlinked="False" disallowedupgrades="" spritedepth="0.55" hiddeningame="True" hideinassemblypreview="true">
    <Holdable holdpos="0,0" holdangle="0" swingamount="0,0" swingspeed="0" swingwhenholding="False" swingwhenaiming="False" swingwhenusing="False" pickingtime="0" canbepicked="True" allowingameediting="True" msg="ItemMsgPickUpSelect" />
    <Wire pickingtime="0" canbepicked="False" allowingameediting="True" msg="" nodes="56.5;73;-310;150" />
  </Item>
  <Item name="" identifier="blackwire" ID="73" rect="50075,-10232,42,16"  rotation="0" scale="0.5" spritecolor="50,50,50,255" inventoryiconcolor="50,50,50,255" containercolor="255,255,255,255" condition="100" tags="smallitem,wire" displaysidebysidewhenlinked="False" disallowedupgrades="" spritedepth="0.55" hiddeningame="True" hideinassemblypreview="true">
    <Holdable holdpos="0,0" holdangle="0" swingamount="0,0" swingspeed="0" swingwhenholding="False" swingwhenaiming="False" swingwhenusing="False" pickingtime="0" canbepicked="True" allowingameediting="True" msg="ItemMsgPickUpSelect" />
    <Wire pickingtime="0" canbepicked="False" allowingameediting="True" msg="" nodes="56.5;73;1;1" />
  </Item>
  <Item name="" identifier="blackwire" ID="72" rect="50075,-10232,42,16"  rotation="0" scale="0.5" spritecolor="50,50,50,255" inventoryiconcolor="50,50,50,255" containercolor="255,255,255,255" condition="100" tags="smallitem,wire" displaysidebysidewhenlinked="False" disallowedupgrades="" spritedepth="0.55" hiddeningame="True" hideinassemblypreview="true">
    <Holdable holdpos="0,0" holdangle="0" swingamount="0,0" swingspeed="0" swingwhenholding="False" swingwhenaiming="False" swingwhenusing="False" pickingtime="0" canbepicked="True" allowingameediting="True" msg="ItemMsgPickUpSelect" />
    <Wire pickingtime="0" canbepicked="False" allowingameediting="True" msg="" nodes="55.5;57.5;-310;150" />
  </Item>
  <Item name="" identifier="blackwire" ID="71" rect="50075,-10232,42,16"  rotation="0" scale="0.5" spritecolor="50,50,50,255" inventoryiconcolor="50,50,50,255" containercolor="255,255,255,255" condition="100" tags="smallitem,wire" displaysidebysidewhenlinked="False" disallowedupgrades="" spritedepth="0.55" hiddeningame="True" hideinassemblypreview="true">
    <Holdable holdpos="0,0" holdangle="0" swingamount="0,0" swingspeed="0" swingwhenholding="False" swingwhenaiming="False" swingwhenusing="False" pickingtime="0" canbepicked="True" allowingameediting="True" msg="ItemMsgPickUpSelect" />
    <Wire pickingtime="0" canbepicked="False" allowingameediting="True" msg="" nodes="55.5;57.5;1;-138" />
  </Item>
  <Item name="" identifier="blackwire" ID="70" rect="50075,-10232,42,16"  rotation="0" scale="0.5" spritecolor="50,50,50,255" inventoryiconcolor="50,50,50,255" containercolor="255,255,255,255" condition="100" tags="smallitem,wire" displaysidebysidewhenlinked="False" disallowedupgrades="" spritedepth="0.55" hiddeningame="True" hideinassemblypreview="true">
    <Holdable holdpos="0,0" holdangle="0" swingamount="0,0" swingspeed="0" swingwhenholding="False" swingwhenaiming="False" swingwhenusing="False" pickingtime="0" canbepicked="True" allowingameediting="True" msg="ItemMsgPickUpSelect" />
    <Wire pickingtime="0" canbepicked="False" allowingameediting="True" msg="" nodes="-104.5;57.5;-310;150" />
  </Item>
  <Item name="" identifier="bluewire" ID="69" rect="50075,-10232,42,16"  rotation="0" scale="0.5" spritecolor="51,121,173,255" inventoryiconcolor="51,121,173,255" containercolor="255,255,255,255" condition="100" tags="smallitem,wire" displaysidebysidewhenlinked="False" disallowedupgrades="" spritedepth="0.55" hiddeningame="True" hideinassemblypreview="true">
    <Holdable holdpos="0,0" holdangle="0" swingamount="0,0" swingspeed="0" swingwhenholding="False" swingwhenaiming="False" swingwhenusing="False" pickingtime="0" canbepicked="True" allowingameediting="True" msg="ItemMsgPickUpSelect" />
    <Wire pickingtime="0" canbepicked="False" allowingameediting="True" msg="" nodes="-2;2;-310;150" />
  </Item>
  <Item name="" identifier="bluewire" ID="67" rect="50075,-10232,42,16"  rotation="0" scale="0.5" spritecolor="51,121,173,255" inventoryiconcolor="51,121,173,255" containercolor="255,255,255,255" condition="100" tags="smallitem,wire" displaysidebysidewhenlinked="False" disallowedupgrades="" spritedepth="0.55" hiddeningame="True" hideinassemblypreview="true">
    <Holdable holdpos="0,0" holdangle="0" swingamount="0,0" swingspeed="0" swingwhenholding="False" swingwhenaiming="False" swingwhenusing="False" pickingtime="0" canbepicked="True" allowingameediting="True" msg="ItemMsgPickUpSelect" />
    <Wire pickingtime="0" canbepicked="False" allowingameediting="True" msg="" nodes="-2;2;312;152" />
  </Item>
  <Item name="" identifier="bluewire" ID="66" rect="50075,-10232,42,16"  rotation="0" scale="0.5" spritecolor="51,121,173,255" inventoryiconcolor="51,121,173,255" containercolor="255,255,255,255" condition="100" tags="smallitem,wire" displaysidebysidewhenlinked="False" disallowedupgrades="" spritedepth="0.55" hiddeningame="True" hideinassemblypreview="true">
    <Holdable holdpos="0,0" holdangle="0" swingamount="0,0" swingspeed="0" swingwhenholding="False" swingwhenaiming="False" swingwhenusing="False" pickingtime="0" canbepicked="True" allowingameediting="True" msg="ItemMsgPickUpSelect" />
    <Wire pickingtime="0" canbepicked="False" allowingameediting="True" msg="" nodes="-2;2;314;-138" />
  </Item>
  <Item name="" identifier="greenwire" ID="65" rect="50075,-10232,42,16"  rotation="0" scale="0.5" spritecolor="56,143,111,255" inventoryiconcolor="56,143,111,255" containercolor="255,255,255,255" condition="100" tags="smallitem,wire" displaysidebysidewhenlinked="False" disallowedupgrades="" spritedepth="0.55" hiddeningame="True" hideinassemblypreview="true">
    <Holdable holdpos="0,0" holdangle="0" swingamount="0,0" swingspeed="0" swingwhenholding="False" swingwhenaiming="False" swingwhenusing="False" pickingtime="0" canbepicked="True" allowingameediting="True" msg="ItemMsgPickUpSelect" />
    <Wire pickingtime="0" canbepicked="False" allowingameediting="True" msg="" nodes="23.5;-54.5;1;-138" />
  </Item>
  <Item name="" identifier="greenwire" ID="64" rect="50075,-10232,42,16"  rotation="0" scale="0.5" spritecolor="56,143,111,255" inventoryiconcolor="56,143,111,255" containercolor="255,255,255,255" condition="100" tags="smallitem,wire" displaysidebysidewhenlinked="False" disallowedupgrades="" spritedepth="0.55" hiddeningame="True" hideinassemblypreview="true">
    <Holdable holdpos="0,0" holdangle="0" swingamount="0,0" swingspeed="0" swingwhenholding="False" swingwhenaiming="False" swingwhenusing="False" pickingtime="0" canbepicked="True" allowingameediting="True" msg="ItemMsgPickUpSelect" />
    <Wire pickingtime="0" canbepicked="False" allowingameediting="True" msg="" nodes="-2;2;23.5;-54.5" />
  </Item>
  <Item name="" identifier="orangewire" ID="63" rect="50075,-10232,42,16"  rotation="0" scale="0.5" spritecolor="255,140,13,255" inventoryiconcolor="255,140,13,255" containercolor="255,255,255,255" condition="100" tags="smallitem,wire" displaysidebysidewhenlinked="False" disallowedupgrades="" spritedepth="0.55" hiddeningame="True" hideinassemblypreview="true">
    <Holdable holdpos="0,0" holdangle="0" swingamount="0,0" swingspeed="0" swingwhenholding="False" swingwhenaiming="False" swingwhenusing="False" pickingtime="0" canbepicked="True" allowingameediting="True" msg="ItemMsgPickUpSelect" />
    <Wire pickingtime="0" canbepicked="False" allowingameediting="True" msg="" nodes="8;280;0;40" />
  </Item>
  <Item name="" identifier="blackwire" ID="62" rect="50075,-10232,42,16"  rotation="0" scale="0.5" spritecolor="50,50,50,255" inventoryiconcolor="50,50,50,255" containercolor="255,255,255,255" condition="100" tags="smallitem,wire" displaysidebysidewhenlinked="False" disallowedupgrades="" spritedepth="0.55" hiddeningame="True" hideinassemblypreview="true">
    <Holdable holdpos="0,0" holdangle="0" swingamount="0,0" swingspeed="0" swingwhenholding="False" swingwhenaiming="False" swingwhenusing="False" pickingtime="0" canbepicked="True" allowingameediting="True" msg="ItemMsgPickUpSelect" />
    <Wire pickingtime="0" canbepicked="False" allowingameediting="True" msg="" nodes="8;280;24.5;73" />
  </Item>
  <Item name="" identifier="blackwire" ID="61" rect="50075,-10232,42,16"  rotation="0" scale="0.5" spritecolor="50,50,50,255" inventoryiconcolor="50,50,50,255" containercolor="255,255,255,255" condition="100" tags="smallitem,wire" displaysidebysidewhenlinked="False" disallowedupgrades="" spritedepth="0.55" hiddeningame="True" hideinassemblypreview="true">
    <Holdable holdpos="0,0" holdangle="0" swingamount="0,0" swingspeed="0" swingwhenholding="False" swingwhenaiming="False" swingwhenusing="False" pickingtime="0" canbepicked="True" allowingameediting="True" msg="ItemMsgPickUpSelect" />
    <Wire pickingtime="0" canbepicked="False" allowingameediting="True" msg="" nodes="8;280;-8.5;57.5" />
  </Item>
  <Item name="" identifier="blackwire" ID="60" rect="50075,-10232,42,16"  rotation="0" scale="0.5" spritecolor="50,50,50,255" inventoryiconcolor="50,50,50,255" containercolor="255,255,255,255" condition="100" tags="smallitem,wire" displaysidebysidewhenlinked="False" disallowedupgrades="" spritedepth="0.55" hiddeningame="True" hideinassemblypreview="true">
    <Holdable holdpos="0,0" holdangle="0" swingamount="0,0" swingspeed="0" swingwhenholding="False" swingwhenaiming="False" swingwhenusing="False" pickingtime="0" canbepicked="True" allowingameediting="True" msg="ItemMsgPickUpSelect" />
    <Wire pickingtime="0" canbepicked="False" allowingameediting="True" msg="" nodes="8;280;23.5;57.5" />
  </Item>
  <Item name="" identifier="bluewire" ID="59" rect="50075,-10232,42,16"  rotation="0" scale="0.5" spritecolor="51,121,173,255" inventoryiconcolor="51,121,173,255" containercolor="255,255,255,255" condition="100" tags="smallitem,wire" displaysidebysidewhenlinked="False" disallowedupgrades="" spritedepth="0.55" hiddeningame="True" hideinassemblypreview="true">
    <Holdable holdpos="0,0" holdangle="0" swingamount="0,0" swingspeed="0" swingwhenholding="False" swingwhenaiming="False" swingwhenusing="False" pickingtime="0" canbepicked="True" allowingameediting="True" msg="ItemMsgPickUpSelect" />
    <Wire pickingtime="0" canbepicked="False" allowingameediting="True" msg="" nodes="8;280;-2;2" />
  </Item>
  <Item name="" identifier="blackwire" ID="58" rect="50075,-10232,42,16"  rotation="0" scale="0.5" spritecolor="50,50,50,255" inventoryiconcolor="50,50,50,255" containercolor="255,255,255,255" condition="100" tags="smallitem,wire" displaysidebysidewhenlinked="False" disallowedupgrades="" spritedepth="0.55" hiddeningame="True" hideinassemblypreview="true">
    <Holdable holdpos="0,0" holdangle="0" swingamount="0,0" swingspeed="0" swingwhenholding="False" swingwhenaiming="False" swingwhenusing="False" pickingtime="0" canbepicked="True" allowingameediting="True" msg="ItemMsgPickUpSelect" />
    <Wire pickingtime="0" canbepicked="False" allowingameediting="True" msg="" nodes="8;280;-8.5;73" />
  </Item>
  <Item name="" identifier="orangewire" ID="57" rect="50075,-10232,42,16"  rotation="0" scale="0.5" spritecolor="255,140,13,255" inventoryiconcolor="255,140,13,255" containercolor="255,255,255,255" condition="100" tags="smallitem,wire" displaysidebysidewhenlinked="False" disallowedupgrades="" spritedepth="0.55" hiddeningame="True" hideinassemblypreview="true">
    <Holdable holdpos="0,0" holdangle="0" swingamount="0,0" swingspeed="0" swingwhenholding="False" swingwhenaiming="False" swingwhenusing="False" pickingtime="0" canbepicked="True" allowingameediting="True" msg="ItemMsgPickUpSelect" />
    <Wire pickingtime="0" canbepicked="False" allowingameediting="True" msg="" nodes="-116;-267;-35;-23" />
  </Item>
  <Item name="" identifier="blackwire" ID="56" rect="50075,-10232,42,16"  rotation="0" scale="0.5" spritecolor="50,50,50,255" inventoryiconcolor="50,50,50,255" containercolor="255,255,255,255" condition="100" tags="smallitem,wire" displaysidebysidewhenlinked="False" disallowedupgrades="" spritedepth="0.55" hiddeningame="True" hideinassemblypreview="true">
    <Holdable holdpos="0,0" holdangle="0" swingamount="0,0" swingspeed="0" swingwhenholding="False" swingwhenaiming="False" swingwhenusing="False" pickingtime="0" canbepicked="True" allowingameediting="True" msg="ItemMsgPickUpSelect" />
    <Wire pickingtime="0" canbepicked="False" allowingameediting="True" msg="" nodes="-116;-267;-104.5;57.5" />
  </Item>
  <Item name="" identifier="signalcheckcomponent" ID="35" rect="-80,64,15,13"  rotation="0" scale="0.5" spritecolor="255,255,255,255" inventoryiconcolor="255,255,255,255" containercolor="255,255,255,255" condition="100" tags="smallitem,logic" displaysidebysidewhenlinked="False" disallowedupgrades="" spritedepth="0.8" hiddeningame="True">
    <SignalCheckComponent output="0" falseoutput="" targetsignal="1" pickingtime="0" canbepicked="False" allowingameediting="True" msg="" />
    <Holdable attached="True" holdpos="0,0" holdangle="0" swingamount="0,0" swingspeed="0" swingwhenholding="False" swingwhenaiming="False" swingwhenusing="False" pickingtime="5" canbepicked="True" allowingameediting="True" msg="ItemMsgDetachWrench">
      <requireditem items="wrench" type="Equipped" optional="false" ignoreineditor="false" />
    </Holdable>
    <ConnectionPanel locked="False" pickingtime="0" canbepicked="False" allowingameediting="True" msg="ItemMsgRewireScrewdriver">
      <requireditem items="screwdriver" type="Equipped" optional="false" ignoreineditor="false" />
      <input name="signal_in">
        <link w="164" />
      </input>
      <input name="set_output" />
      <input name="set_targetsignal" />
      <output name="signal_out">
        <link w="165" />
      </output>
    </ConnectionPanel>
  </Item>
  <Item name="" identifier="signalcheckcomponent" ID="34" rect="-48,64,15,13"  rotation="0" scale="0.5" spritecolor="255,255,255,255" inventoryiconcolor="255,255,255,255" containercolor="255,255,255,255" condition="100" tags="smallitem,logic" displaysidebysidewhenlinked="False" disallowedupgrades="" spritedepth="0.8" hiddeningame="True">
    <SignalCheckComponent output="0" falseoutput="" targetsignal="1" pickingtime="0" canbepicked="False" allowingameediting="True" msg="" />
    <Holdable attached="True" holdpos="0,0" holdangle="0" swingamount="0,0" swingspeed="0" swingwhenholding="False" swingwhenaiming="False" swingwhenusing="False" pickingtime="5" canbepicked="True" allowingameediting="True" msg="ItemMsgDetachWrench">
      <requireditem items="wrench" type="Equipped" optional="false" ignoreineditor="false" />
    </Holdable>
    <ConnectionPanel locked="False" pickingtime="0" canbepicked="False" allowingameediting="True" msg="ItemMsgRewireScrewdriver">
      <requireditem items="screwdriver" type="Equipped" optional="false" ignoreineditor="false" />
      <input name="signal_in">
        <link w="162" />
      </input>
      <input name="set_output" />
      <input name="set_targetsignal" />
      <output name="signal_out">
        <link w="163" />
      </output>
    </ConnectionPanel>
  </Item>
  <Item name="" identifier="signalcheckcomponent" ID="33" rect="-16,64,15,13"  rotation="0" scale="0.5" spritecolor="255,255,255,255" inventoryiconcolor="255,255,255,255" containercolor="255,255,255,255" condition="100" tags="smallitem,logic" displaysidebysidewhenlinked="False" disallowedupgrades="" spritedepth="0.8" hiddeningame="True">
    <SignalCheckComponent output="0" falseoutput="" targetsignal="1" pickingtime="0" canbepicked="False" allowingameediting="True" msg="" />
    <Holdable attached="True" holdpos="0,0" holdangle="0" swingamount="0,0" swingspeed="0" swingwhenholding="False" swingwhenaiming="False" swingwhenusing="False" pickingtime="5" canbepicked="True" allowingameediting="True" msg="ItemMsgDetachWrench">
      <requireditem items="wrench" type="Equipped" optional="false" ignoreineditor="false" />
    </Holdable>
    <ConnectionPanel locked="False" pickingtime="0" canbepicked="False" allowingameediting="True" msg="ItemMsgRewireScrewdriver">
      <requireditem items="screwdriver" type="Equipped" optional="false" ignoreineditor="false" />
      <input name="signal_in">
        <link w="61" />
      </input>
      <input name="set_output" />
      <input name="set_targetsignal" />
      <output name="signal_out">
        <link w="161" />
      </output>
    </ConnectionPanel>
  </Item>
  <Item name="" identifier="signalcheckcomponent" ID="32" rect="16,64,15,13"  rotation="0" scale="0.5" spritecolor="255,255,255,255" inventoryiconcolor="255,255,255,255" containercolor="255,255,255,255" condition="100" tags="smallitem,logic" displaysidebysidewhenlinked="False" disallowedupgrades="" spritedepth="0.8" hiddeningame="True">
    <SignalCheckComponent output="0" falseoutput="" targetsignal="1" pickingtime="0" canbepicked="False" allowingameediting="True" msg="" />
    <Holdable attached="True" holdpos="0,0" holdangle="0" swingamount="0,0" swingspeed="0" swingwhenholding="False" swingwhenaiming="False" swingwhenusing="False" pickingtime="5" canbepicked="True" allowingameediting="True" msg="ItemMsgDetachWrench">
      <requireditem items="wrench" type="Equipped" optional="false" ignoreineditor="false" />
    </Holdable>
    <ConnectionPanel locked="False" pickingtime="0" canbepicked="False" allowingameediting="True" msg="ItemMsgRewireScrewdriver">
      <requireditem items="screwdriver" type="Equipped" optional="false" ignoreineditor="false" />
      <input name="signal_in">
        <link w="160" />
      </input>
      <input name="set_output" />
      <input name="set_targetsignal" />
      <output name="signal_out">
        <link w="60" />
      </output>
    </ConnectionPanel>
  </Item>
  <Item name="" identifier="andcomponent" ID="31" rect="-80,80,15,14"  rotation="0" scale="0.5" spritecolor="255,255,255,255" inventoryiconcolor="255,255,255,255" containercolor="255,255,255,255" condition="100" tags="smallitem,logic" displaysidebysidewhenlinked="False" disallowedupgrades="" spritedepth="0.8" hiddeningame="True">
    <AndComponent timeframe="0" output="1" falseoutput="" pickingtime="0" canbepicked="False" allowingameediting="True" msg="" />
    <Holdable attached="True" holdpos="0,0" holdangle="0" swingamount="0,0" swingspeed="0" swingwhenholding="False" swingwhenaiming="False" swingwhenusing="False" pickingtime="5" canbepicked="True" allowingameediting="True" msg="ItemMsgDetachWrench">
      <requireditem items="wrench" type="Equipped" optional="false" ignoreineditor="false" />
    </Holdable>
    <ConnectionPanel locked="False" pickingtime="0" canbepicked="False" allowingameediting="True" msg="ItemMsgRewireScrewdriver">
      <requireditem items="screwdriver" type="Equipped" optional="false" ignoreineditor="false" />
      <input name="signal_in1">
        <link w="157" />
      </input>
      <input name="signal_in2">
        <link w="158" />
      </input>
      <input name="set_output" />
      <output name="signal_out">
        <link w="159" />
      </output>
    </ConnectionPanel>
  </Item>
  <Item name="" identifier="andcomponent" ID="30" rect="-48,80,15,14"  rotation="0" scale="0.5" spritecolor="255,255,255,255" inventoryiconcolor="255,255,255,255" containercolor="255,255,255,255" condition="100" tags="smallitem,logic" displaysidebysidewhenlinked="False" disallowedupgrades="" spritedepth="0.8" hiddeningame="True">
    <AndComponent timeframe="0" output="1" falseoutput="" pickingtime="0" canbepicked="False" allowingameediting="True" msg="" />
    <Holdable attached="True" holdpos="0,0" holdangle="0" swingamount="0,0" swingspeed="0" swingwhenholding="False" swingwhenaiming="False" swingwhenusing="False" pickingtime="5" canbepicked="True" allowingameediting="True" msg="ItemMsgDetachWrench">
      <requireditem items="wrench" type="Equipped" optional="false" ignoreineditor="false" />
    </Holdable>
    <ConnectionPanel locked="False" pickingtime="0" canbepicked="False" allowingameediting="True" msg="ItemMsgRewireScrewdriver">
      <requireditem items="screwdriver" type="Equipped" optional="false" ignoreineditor="false" />
      <input name="signal_in1">
        <link w="154" />
      </input>
      <input name="signal_in2">
        <link w="155" />
      </input>
      <input name="set_output" />
      <output name="signal_out">
        <link w="156" />
      </output>
    </ConnectionPanel>
  </Item>
  <Item name="" identifier="andcomponent" ID="29" rect="-16,80,15,14"  rotation="0" scale="0.5" spritecolor="255,255,255,255" inventoryiconcolor="255,255,255,255" containercolor="255,255,255,255" condition="100" tags="smallitem,logic" displaysidebysidewhenlinked="False" disallowedupgrades="" spritedepth="0.8" hiddeningame="True">
    <AndComponent timeframe="0" output="1" falseoutput="" pickingtime="0" canbepicked="False" allowingameediting="True" msg="" />
    <Holdable attached="True" holdpos="0,0" holdangle="0" swingamount="0,0" swingspeed="0" swingwhenholding="False" swingwhenaiming="False" swingwhenusing="False" pickingtime="5" canbepicked="True" allowingameediting="True" msg="ItemMsgDetachWrench">
      <requireditem items="wrench" type="Equipped" optional="false" ignoreineditor="false" />
    </Holdable>
    <ConnectionPanel locked="False" pickingtime="0" canbepicked="False" allowingameediting="True" msg="ItemMsgRewireScrewdriver">
      <requireditem items="screwdriver" type="Equipped" optional="false" ignoreineditor="false" />
      <input name="signal_in1">
        <link w="78" />
      </input>
      <input name="signal_in2">
        <link w="79" />
      </input>
      <input name="set_output" />
      <output name="signal_out">
        <link w="58" />
      </output>
    </ConnectionPanel>
  </Item>
  <Item name="" identifier="andcomponent" ID="28" rect="17,80,15,14"  rotation="0" scale="0.5" spritecolor="255,255,255,255" inventoryiconcolor="255,255,255,255" containercolor="255,255,255,255" condition="100" tags="smallitem,logic" displaysidebysidewhenlinked="False" disallowedupgrades="" spritedepth="0.8" hiddeningame="True">
    <AndComponent timeframe="0" output="1" falseoutput="" pickingtime="0" canbepicked="False" allowingameediting="True" msg="" />
    <Holdable attached="True" holdpos="0,0" holdangle="0" swingamount="0,0" swingspeed="0" swingwhenholding="False" swingwhenaiming="False" swingwhenusing="False" pickingtime="5" canbepicked="True" allowingameediting="True" msg="ItemMsgDetachWrench">
      <requireditem items="wrench" type="Equipped" optional="false" ignoreineditor="false" />
    </Holdable>
    <ConnectionPanel locked="False" pickingtime="0" canbepicked="False" allowingameediting="True" msg="ItemMsgRewireScrewdriver">
      <requireditem items="screwdriver" type="Equipped" optional="false" ignoreineditor="false" />
      <input name="signal_in1">
        <link w="62" />
      </input>
      <input name="signal_in2">
        <link w="76" />
      </input>
      <input name="set_output" />
      <output name="signal_out">
        <link w="77" />
      </output>
    </ConnectionPanel>
  </Item>
  <Item name="" identifier="andcomponent" ID="27" rect="49,80,15,14"  rotation="0" scale="0.5" spritecolor="255,255,255,255" inventoryiconcolor="255,255,255,255" containercolor="255,255,255,255" condition="100" tags="smallitem,logic" displaysidebysidewhenlinked="False" disallowedupgrades="" spritedepth="0.8" hiddeningame="True">
    <AndComponent timeframe="0" output="1" falseoutput="" pickingtime="0" canbepicked="False" allowingameediting="True" msg="" />
    <Holdable attached="True" holdpos="0,0" holdangle="0" swingamount="0,0" swingspeed="0" swingwhenholding="False" swingwhenaiming="False" swingwhenusing="False" pickingtime="5" canbepicked="True" allowingameediting="True" msg="ItemMsgDetachWrench">
      <requireditem items="wrench" type="Equipped" optional="false" ignoreineditor="false" />
    </Holdable>
    <ConnectionPanel locked="False" pickingtime="0" canbepicked="False" allowingameediting="True" msg="ItemMsgRewireScrewdriver">
      <requireditem items="screwdriver" type="Equipped" optional="false" ignoreineditor="false" />
      <input name="signal_in1">
        <link w="73" />
      </input>
      <input name="signal_in2">
        <link w="74" />
      </input>
      <input name="set_output" />
      <output name="signal_out">
        <link w="75" />
      </output>
    </ConnectionPanel>
  </Item>
  <Item name="" identifier="signalcheckcomponent" ID="26" rect="48,64,15,13"  rotation="0" scale="0.5" spritecolor="255,255,255,255" inventoryiconcolor="255,255,255,255" containercolor="255,255,255,255" condition="100" tags="smallitem,logic" displaysidebysidewhenlinked="False" disallowedupgrades="" spritedepth="0.8" hiddeningame="True">
    <SignalCheckComponent output="0" falseoutput="" targetsignal="1" pickingtime="0" canbepicked="False" allowingameediting="True" msg="" />
    <Holdable attached="True" holdpos="0,0" holdangle="0" swingamount="0,0" swingspeed="0" swingwhenholding="False" swingwhenaiming="False" swingwhenusing="False" pickingtime="5" canbepicked="True" allowingameediting="True" msg="ItemMsgDetachWrench">
      <requireditem items="wrench" type="Equipped" optional="false" ignoreineditor="false" />
    </Holdable>
    <ConnectionPanel locked="False" pickingtime="0" canbepicked="False" allowingameediting="True" msg="ItemMsgRewireScrewdriver">
      <requireditem items="screwdriver" type="Equipped" optional="false" ignoreineditor="false" />
      <input name="signal_in">
        <link w="71" />
      </input>
      <input name="set_output" />
      <input name="set_targetsignal" />
      <output name="signal_out">
        <link w="72" />
      </output>
    </ConnectionPanel>
  </Item>
  <Item name="" identifier="signalcheckcomponent" ID="25" rect="-112,64,15,13"  rotation="0" scale="0.5" spritecolor="255,255,255,255" inventoryiconcolor="255,255,255,255" containercolor="255,255,255,255" condition="100" tags="smallitem,logic" displaysidebysidewhenlinked="False" disallowedupgrades="" spritedepth="0.8" hiddeningame="True">
    <SignalCheckComponent output="1" falseoutput="0" targetsignal="1" pickingtime="0" canbepicked="False" allowingameediting="True" msg="" />
    <Holdable attached="True" holdpos="0,0" holdangle="0" swingamount="0,0" swingspeed="0" swingwhenholding="False" swingwhenaiming="False" swingwhenusing="False" pickingtime="5" canbepicked="True" allowingameediting="True" msg="ItemMsgDetachWrench">
      <requireditem items="wrench" type="Equipped" optional="false" ignoreineditor="false" />
    </Holdable>
    <ConnectionPanel locked="False" pickingtime="0" canbepicked="False" allowingameediting="True" msg="ItemMsgRewireScrewdriver">
      <requireditem items="screwdriver" type="Equipped" optional="false" ignoreineditor="false" />
      <input name="signal_in">
        <link w="70" />
      </input>
      <input name="set_output" />
      <input name="set_targetsignal" />
      <output name="signal_out">
        <link w="56" />
      </output>
    </ConnectionPanel>
  </Item>
  <Item name="" identifier="motiondetector" ID="24" rect="-14,14,24,24" noninteractable="True" rotation="0" scale="0.5" spritecolor="255,255,255,255" inventoryiconcolor="255,255,255,255" containercolor="255,255,255,255" condition="100" tags="smallitem,sensor" displaysidebysidewhenlinked="False" disallowedupgrades="" spritedepth="0.8" hiddeningame="False">
    <MotionSensor onlyhumans="True" ignoredead="False" rangex="470" rangey="440" detectoffset="0,0" output="" falseoutput="0" minimumvelocity="0" pickingtime="0" canbepicked="False" allowingameediting="True" msg="" />
    <Holdable attached="True" holdpos="0,0" holdangle="0" swingamount="0,0" swingspeed="0" swingwhenholding="False" swingwhenaiming="False" swingwhenusing="False" pickingtime="5" canbepicked="True" allowingameediting="True" msg="ItemMsgDetachWrench">
      <requireditem items="wrench" type="Equipped" optional="false" ignoreineditor="false" />
    </Holdable>
    <ConnectionPanel locked="False" pickingtime="0" canbepicked="False" allowingameediting="True" msg="ItemMsgRewireScrewdriver">
      <requireditem items="screwdriver" type="Equipped" optional="false" ignoreineditor="false" />
      <output name="state_out">
        <link w="59" />
        <link w="64" />
        <link w="66" />
        <link w="67" />
        <link w="69" />
      </output>
    </ConnectionPanel>
  </Item>
  <Item name="" identifier="signalcheckcomponent" ID="23" rect="16,-48,15,13"  rotation="0" scale="0.5" spritecolor="255,255,255,255" inventoryiconcolor="255,255,255,255" containercolor="255,255,255,255" condition="100" tags="smallitem,logic" displaysidebysidewhenlinked="False" disallowedupgrades="" spritedepth="0.8" hiddeningame="False">
    <SignalCheckComponent output="1" falseoutput="" targetsignal="0" pickingtime="0" canbepicked="False" allowingameediting="True" msg="" />
    <Holdable attached="True" holdpos="0,0" holdangle="0" swingamount="0,0" swingspeed="0" swingwhenholding="False" swingwhenaiming="False" swingwhenusing="False" pickingtime="5" canbepicked="True" allowingameediting="True" msg="ItemMsgDetachWrench">
      <requireditem items="wrench" type="Equipped" optional="false" ignoreineditor="false" />
    </Holdable>
    <ConnectionPanel locked="False" pickingtime="0" canbepicked="False" allowingameediting="True" msg="ItemMsgRewireScrewdriver">
      <requireditem items="screwdriver" type="Equipped" optional="false" ignoreineditor="false" />
      <input name="signal_in">
        <link w="64" />
      </input>
      <input name="set_output" />
      <input name="set_targetsignal" />
      <output name="signal_out">
        <link w="65" />
      </output>
    </ConnectionPanel>
  </Item>
  <Item name="" identifier="alienlightcomponent" ID="43" rect="29,30,16,16" noninteractable="True" rotation="0" scale="1" spritecolor="255,255,255,255" inventoryiconcolor="255,255,255,255" containercolor="255,255,255,255" condition="100" tags="smallitem,alienlight,light" displaysidebysidewhenlinked="False" disallowedupgrades="" spritedepth="0.8" hiddeningame="False">
    <LightComponent range="20" castshadows="False" drawbehindsubs="False" ison="True" flicker="0" flickerspeed="1" blinkfrequency="0" lightcolor="0,255,255,255" isactive="True" minvoltage="0" powerconsumption="0" vulnerabletoemp="True" pickingtime="0" canbepicked="False" allowingameediting="False" msg="" />
    <ConnectionPanel locked="False" pickingtime="0" canbepicked="False" allowingameediting="True" msg="ItemMsgRewireScrewdriver">
      <requireditem items="screwdriver" type="Equipped" optional="false" ignoreineditor="false" />
      <input name="toggle" />
      <input name="set_state">
        <link w="169" />
      </input>
      <input name="set_color" />
    </ConnectionPanel>
  </Item>
  <Item name="" identifier="alienlightcomponent" ID="42" rect="-8,48,16,16" noninteractable="True" rotation="0" scale="1" spritecolor="255,255,255,255" inventoryiconcolor="255,255,255,255" containercolor="255,255,255,255" condition="100" tags="smallitem,alienlight,light" displaysidebysidewhenlinked="False" disallowedupgrades="" spritedepth="0.8" hiddeningame="False">
    <LightComponent range="20" castshadows="False" drawbehindsubs="False" ison="True" flicker="0" flickerspeed="1" blinkfrequency="0" lightcolor="0,255,255,255" isactive="True" minvoltage="0" powerconsumption="0" vulnerabletoemp="True" pickingtime="0" canbepicked="False" allowingameediting="False" msg="" />
    <ConnectionPanel locked="False" pickingtime="0" canbepicked="False" allowingameediting="True" msg="ItemMsgRewireScrewdriver">
      <requireditem items="screwdriver" type="Equipped" optional="false" ignoreineditor="false" />
      <input name="toggle" />
      <input name="set_state">
        <link w="63" />
      </input>
      <input name="set_color" />
    </ConnectionPanel>
  </Item>
  <Item name="" identifier="alienlightcomponent" ID="41" rect="-43,30,16,16" noninteractable="True" rotation="0" scale="1" spritecolor="255,255,255,255" inventoryiconcolor="255,255,255,255" containercolor="255,255,255,255" condition="100" tags="smallitem,alienlight,light" displaysidebysidewhenlinked="False" disallowedupgrades="" spritedepth="0.8" hiddeningame="False">
    <LightComponent range="20" castshadows="False" drawbehindsubs="False" ison="True" flicker="0" flickerspeed="1" blinkfrequency="0" lightcolor="0,255,255,255" isactive="True" minvoltage="0" powerconsumption="0" vulnerabletoemp="True" pickingtime="0" canbepicked="False" allowingameediting="False" msg="" />
    <ConnectionPanel locked="False" pickingtime="0" canbepicked="False" allowingameediting="True" msg="ItemMsgRewireScrewdriver">
      <requireditem items="screwdriver" type="Equipped" optional="false" ignoreineditor="false" />
      <input name="toggle" />
      <input name="set_state">
        <link w="168" />
      </input>
      <input name="set_color" />
    </ConnectionPanel>
  </Item>
  <Item name="" identifier="alienlightcomponent" ID="40" rect="-43,-15,16,16" noninteractable="True" rotation="0" scale="1" spritecolor="255,255,255,255" inventoryiconcolor="255,255,255,255" containercolor="255,255,255,255" condition="100" tags="smallitem,alienlight,light" displaysidebysidewhenlinked="False" disallowedupgrades="" spritedepth="0.8" hiddeningame="False">
    <LightComponent range="20" castshadows="False" drawbehindsubs="False" ison="True" flicker="0" flickerspeed="1" blinkfrequency="0" lightcolor="0,255,255,255" isactive="True" minvoltage="0" powerconsumption="0" vulnerabletoemp="True" pickingtime="0" canbepicked="False" allowingameediting="False" msg="" />
    <ConnectionPanel locked="False" pickingtime="0" canbepicked="False" allowingameediting="True" msg="ItemMsgRewireScrewdriver">
      <requireditem items="screwdriver" type="Equipped" optional="false" ignoreineditor="false" />
      <input name="toggle" />
      <input name="set_state">
        <link w="57" />
      </input>
      <input name="set_color" />
    </ConnectionPanel>
  </Item>
  <Item name="" identifier="alienlightcomponent" ID="39" rect="-7,8,16,16" noninteractable="True" rotation="0" scale="1" spritecolor="255,255,255,255" inventoryiconcolor="255,255,255,255" containercolor="255,255,255,255" condition="100" tags="smallitem,alienlight,light" displaysidebysidewhenlinked="False" disallowedupgrades="" spritedepth="0.8" hiddeningame="False">
    <LightComponent range="30" castshadows="False" drawbehindsubs="False" ison="True" flicker="0" flickerspeed="1" blinkfrequency="0" lightcolor="255,90,0,255" isactive="True" minvoltage="0" powerconsumption="0" vulnerabletoemp="True" pickingtime="0" canbepicked="False" allowingameediting="False" msg="" />
    <ConnectionPanel locked="False" pickingtime="0" canbepicked="False" allowingameediting="True" msg="ItemMsgRewireScrewdriver">
      <requireditem items="screwdriver" type="Equipped" optional="false" ignoreineditor="false" />
      <input name="toggle" />
      <input name="set_state" />
      <input name="set_color" />
    </ConnectionPanel>
  </Item>
  <Item name="" identifier="alienlightcomponent" ID="37" rect="-7,-33,16,16" noninteractable="True" rotation="0" scale="1" spritecolor="255,255,255,255" inventoryiconcolor="255,255,255,255" containercolor="255,255,255,255" condition="100" tags="smallitem,alienlight,light" displaysidebysidewhenlinked="False" disallowedupgrades="" spritedepth="0.8" hiddeningame="False">
    <LightComponent range="20" castshadows="False" drawbehindsubs="False" ison="True" flicker="0" flickerspeed="1" blinkfrequency="0" lightcolor="0,255,255,255" isactive="True" minvoltage="0" powerconsumption="0" vulnerabletoemp="True" pickingtime="0" canbepicked="False" allowingameediting="False" msg="" />
    <ConnectionPanel locked="False" pickingtime="0" canbepicked="False" allowingameediting="True" msg="ItemMsgRewireScrewdriver">
      <requireditem items="screwdriver" type="Equipped" optional="false" ignoreineditor="false" />
      <input name="toggle" />
      <input name="set_state">
        <link w="167" />
      </input>
      <input name="set_color" />
    </ConnectionPanel>
  </Item>
  <Item name="" identifier="alienlightcomponent" ID="36" rect="29,-12,16,16" noninteractable="True" rotation="0" scale="1" spritecolor="255,255,255,255" inventoryiconcolor="255,255,255,255" containercolor="255,255,255,255" condition="100" tags="smallitem,alienlight,light" displaysidebysidewhenlinked="False" disallowedupgrades="" spritedepth="0.8" hiddeningame="False">
    <LightComponent range="20" castshadows="False" drawbehindsubs="False" ison="True" flicker="0" flickerspeed="1" blinkfrequency="0" lightcolor="0,255,255,255" isactive="True" minvoltage="0" powerconsumption="0" vulnerabletoemp="True" pickingtime="0" canbepicked="False" allowingameediting="False" msg="" />
    <ConnectionPanel locked="False" pickingtime="0" canbepicked="False" allowingameediting="True" msg="ItemMsgRewireScrewdriver">
      <requireditem items="screwdriver" type="Equipped" optional="false" ignoreineditor="false" />
      <input name="toggle" />
      <input name="set_state">
        <link w="166" />
      </input>
      <input name="set_color" />
    </ConnectionPanel>
  </Item>
  <Item name="" identifier="alienhatch" ID="47" rect="208,176,208,48" linked=""  rotation="0" scale="1" spritecolor="255,255,255,255" inventoryiconcolor="255,255,255,255" containercolor="255,255,255,255" condition="100" tags="alien,aliendoor" displaysidebysidewhenlinked="False" disallowedupgrades="" spritedepth="0.8" hiddeningame="False">
    <Door openingspeed="3" closingspeed="3" togglecooldown="1" isopen="False" usebetweenoutpostmodules="True" pickingtime="30" canbepicked="False" allowingameediting="True" msg="ItemMsgForceOpenCrowbar">
      <requireditem items="nopick" type="Equipped" optional="false" ignoreineditor="false" />
    </Door>
    <ConnectionPanel locked="False" pickingtime="0" canbepicked="False" allowingameediting="True" msg="">
      <input name="toggle">
        <link w="156" />
      </input>
      <input name="set_state">
        <link w="67" />
        <link w="161" />
      </input>
      <output name="state_out">
        <link w="79" />
        <link w="162" />
        <link w="169" />
      </output>
    </ConnectionPanel>
  </Item>
  <Item name="" identifier="alienhatch" ID="46" rect="-103,-114,208,48" linked=""  rotation="0" scale="1" spritecolor="255,255,255,255" inventoryiconcolor="255,255,255,255" containercolor="255,255,255,255" condition="100" tags="alien,aliendoor" displaysidebysidewhenlinked="False" disallowedupgrades="" spritedepth="0.8" hiddeningame="False">
    <Door openingspeed="3" closingspeed="3" togglecooldown="1" isopen="True" usebetweenoutpostmodules="True" pickingtime="30" canbepicked="False" allowingameediting="True" msg="ItemMsgForceOpenCrowbar">
      <requireditem items="nopick" type="Equipped" optional="false" ignoreineditor="false" />
    </Door>
    <ConnectionPanel locked="False" pickingtime="0" canbepicked="False" allowingameediting="True" msg="">
      <input name="toggle">
        <link w="75" />
      </input>
      <input name="set_state">
        <link w="65" />
        <link w="165" />
      </input>
      <output name="state_out">
        <link w="71" />
        <link w="158" />
        <link w="167" />
      </output>
    </ConnectionPanel>
  </Item>
  <Item name="" identifier="alienhatch" ID="45" rect="-414,174,208,48" linked=""  rotation="0" scale="1" spritecolor="255,255,255,255" inventoryiconcolor="255,255,255,255" containercolor="255,255,255,255" condition="100" tags="alien,aliendoor" displaysidebysidewhenlinked="False" disallowedupgrades="" spritedepth="0.8" hiddeningame="False">
    <Door openingspeed="3" closingspeed="3" togglecooldown="1" isopen="False" usebetweenoutpostmodules="True" pickingtime="30" canbepicked="False" allowingameediting="True" msg="ItemMsgForceOpenCrowbar">
      <requireditem items="nopick" type="Equipped" optional="false" ignoreineditor="false" />
    </Door>
    <ConnectionPanel locked="False" pickingtime="0" canbepicked="False" allowingameediting="True" msg="">
      <input name="toggle">
        <link w="77" />
      </input>
      <input name="set_state">
        <link w="69" />
        <link w="72" />
      </input>
      <output name="state_out">
        <link w="70" />
        <link w="74" />
        <link w="160" />
        <link w="168" />
      </output>
    </ConnectionPanel>
  </Item>
  <Item name="" identifier="alienhatch" ID="44" rect="210,-114,208,48" linked=""  rotation="0" scale="1" spritecolor="255,255,255,255" inventoryiconcolor="255,255,255,255" containercolor="255,255,255,255" condition="100" tags="alien,aliendoor" displaysidebysidewhenlinked="False" disallowedupgrades="" spritedepth="0.8" hiddeningame="False">
    <Door openingspeed="3" closingspeed="3" togglecooldown="1" isopen="False" usebetweenoutpostmodules="True" pickingtime="30" canbepicked="False" allowingameediting="True" msg="ItemMsgForceOpenCrowbar">
      <requireditem items="nopick" type="Equipped" optional="false" ignoreineditor="false" />
    </Door>
    <ConnectionPanel locked="False" pickingtime="0" canbepicked="False" allowingameediting="True" msg="">
      <input name="toggle">
        <link w="159" />
      </input>
      <input name="set_state">
        <link w="66" />
        <link w="163" />
      </input>
      <output name="state_out">
        <link w="155" />
        <link w="164" />
        <link w="166" />
      </output>
    </ConnectionPanel>
  </Item>
  <Item name="" identifier="alienbutton" ID="48" rect="-31,33,64,64"  rotation="0" scale="1" spritecolor="255,255,255,255" inventoryiconcolor="255,255,255,255" containercolor="255,255,255,255" condition="100" tags="smallitem,alien,alienbutton,light" displaysidebysidewhenlinked="False" disallowedupgrades="" spritedepth="0.8" hiddeningame="False">
    <Controller istoggle="False" state="False" pickingtime="0" canbepicked="True" allowingameediting="True" msg="ItemMsgPressSelect" />
    <ConnectionPanel locked="False" pickingtime="0" canbepicked="False" allowingameediting="True" msg="">
      <requireditem items="screwdriver" type="Equipped" optional="false" ignoreineditor="false" />
      <output name="signal_out">
        <link w="73" />
        <link w="76" />
        <link w="78" />
        <link w="154" />
        <link w="157" />
      </output>
    </ConnectionPanel>
    <LightComponent range="15" castshadows="False" drawbehindsubs="False" ison="False" flicker="0" flickerspeed="1" blinkfrequency="0" lightcolor="255,255,255,255" minvoltage="0" powerconsumption="0" vulnerabletoemp="True" pickingtime="0" canbepicked="False" allowingameediting="False" msg="" />
  </Item>
  <Structure name="Ruin Decal 1" identifier="RuinDecal1" ID="49" rect="-112,128,256,256" specialtag="" spritecolor="255,255,255,255" usedropshadow="False" dropshadowoffset="0,0" scale="1" texturescale="1,1" textureoffset="0,0" noaitarget="True" disallowedupgrades="" spritedepth="0.97" hiddeningame="False" />
  <Gap ID="50" horizontal="true" rect="-145,-163,58,208" />
  <Gap ID="51" horizontal="true" rect="-21,384,58,208" />
  <Gap ID="52" horizontal="false" rect="210,-109,208,58" />
  <Gap ID="53" horizontal="false" rect="-414,179,208,58" />
  <Gap ID="54" horizontal="false" rect="-103,-109,208,58" />
  <Gap ID="55" horizontal="false" rect="208,181,208,58" />
</ItemAssembly>